expam/__init__.py
expam/logger.py
expam/main.py
expam/sequences.py
expam/utils.py
expam/classify/__init__.py
expam/classify/classify.py
expam/classify/config.py
expam/classify/process.py
expam/classify/taxonomy.py
expam/cli/__init__.py
expam/cli/build.py
expam/cli/classify.py
expam/cli/main.py
expam/cli/tree.py
expam/cli/utils.py
expam/database/__init__.py
expam/database/build.py
expam/database/config.py
expam/database/db.py
expam/database/shm.py
expam/ext/__init__.py
expam/ext/kmers/__init__.py
expam/ext/kmers/_build/kmers.cpython-39-darwin.so
expam/ext/map/__init__.py
expam/ext/map/_build/map.cpython-39-darwin.so
expam/ext/sets/__init__.py
expam/ext/sets/_build/sets.cpython-39-darwin.so
expam/process/__init__.py
expam/process/classify.py
expam/process/genome.py
expam/process/jobworker.py
expam/process/manager.py
expam/process/piler.py
expam/process/reads.py
expam/sandbox/__init__.py
expam/sandbox/main.py
expam/tree/__init__.py
expam/tree/location.py
expam/tree/simulate.py
expam/tree/sourmash.py
expam/tree/tree.py
expam-1.4.0.7.dist-info/licenses/LICENSE
expam-1.4.0.7.dist-info/METADATA
expam-1.4.0.7.dist-info/WHEEL
expam-1.4.0.7.dist-info/entry_points.txt
expam-1.4.0.7.dist-info/top_level.txt
expam-1.4.0.7.dist-info/RECORD
