Metadata-Version: 2.4
Name: expam
Version: 1.4.0.7
Summary: Metagenomic profiling using a reference phylogeny
Home-page: https://github.com/seansolari/expam
Author: Sean Solari
Author-email: sean.solari@monash.edu
Project-URL: Bug Reports, https://github.com/seansolari/expam/issues
Classifier: Development Status :: 3 - Alpha
Classifier: Intended Audience :: Science/Research
Classifier: Intended Audience :: Developers
Classifier: Topic :: Scientific/Engineering :: Bio-Informatics
Classifier: License :: OSI Approved :: BSD License
Classifier: Programming Language :: Python :: 3
Classifier: Programming Language :: Python :: 3.8
Classifier: Programming Language :: Python :: 3.9
Requires-Python: >=3.8
License-File: LICENSE
Requires-Dist: numpy>=1.22.0
Requires-Dist: Cython
Requires-Dist: ete3
Requires-Dist: matplotlib
Requires-Dist: multiprocess
Requires-Dist: pandas
Requires-Dist: psutil
Requires-Dist: tables
Provides-Extra: treeplot
Requires-Dist: ete3; extra == "treeplot"
Requires-Dist: PyQt5==5.12; extra == "treeplot"
Requires-Dist: sourmash; extra == "treeplot"
Dynamic: author
Dynamic: author-email
Dynamic: classifier
Dynamic: description
Dynamic: description-content-type
Dynamic: home-page
Dynamic: license-file
Dynamic: project-url
Dynamic: provides-extra
Dynamic: requires-dist
Dynamic: requires-python
Dynamic: summary
